base16_admin/__init__.py
base16_admin/apps.py
base16_admin/context_processors.py
base16_admin/py.typed
base16_admin/static/admin/css/base.css
base16_admin/static/admin/css/dark_mode.css
base16_admin/static/admin/css/forms.css
base16_admin/static/admin/css/nav_sidebar.css
base16_admin/static/admin/themes/circus.css
base16_admin/static/admin/themes/cupcake.css
base16_admin/static/admin/themes/tokyo-city-dark.css
base16_admin/static/admin/themes/tokyo-city-light.css
base16_admin/templates/admin/base_site.html
django_base16_admin-0.1.4.dist-info/WHEEL
django_base16_admin-0.1.4.dist-info/METADATA
django_base16_admin-0.1.4.dist-info/RECORD
